__init__.py
visiumlint/__init__.py
visiumlint/main.py
visiumlint-1.9.0.dist-info/LICENSE
visiumlint-1.9.0.dist-info/METADATA
visiumlint-1.9.0.dist-info/WHEEL
visiumlint-1.9.0.dist-info/entry_points.txt
visiumlint-1.9.0.dist-info/top_level.txt
visiumlint-1.9.0.dist-info/RECORD
